evernote/__init__.py
evernote/api/__init__.py
evernote/api/client.py
evernote/edam/__init__.py
evernote/edam/error/__init__.py
evernote/edam/error/constants.py
evernote/edam/error/ttypes.py
evernote/edam/limits/__init__.py
evernote/edam/limits/constants.py
evernote/edam/limits/ttypes.py
evernote/edam/notestore/NoteStore.py
evernote/edam/notestore/__init__.py
evernote/edam/notestore/constants.py
evernote/edam/notestore/ttypes.py
evernote/edam/type/__init__.py
evernote/edam/type/constants.py
evernote/edam/type/ttypes.py
evernote/edam/userstore/UserStore.py
evernote/edam/userstore/__init__.py
evernote/edam/userstore/constants.py
evernote/edam/userstore/ttypes.py
thrift/TSCons.py
thrift/TSerialization.py
thrift/Thrift.py
thrift/__init__.py
thrift/protocol/TBase.py
thrift/protocol/TBinaryProtocol.py
thrift/protocol/TProtocol.py
thrift/protocol/__init__.py
thrift/transport/THttpClient.py
thrift/transport/TTransport.py
thrift/transport/TTwisted.py
thrift/transport/__init__.py
evernote3-1.25.14.dist-info/LICENSE
evernote3-1.25.14.dist-info/METADATA
evernote3-1.25.14.dist-info/NOTICE
evernote3-1.25.14.dist-info/WHEEL
evernote3-1.25.14.dist-info/top_level.txt
evernote3-1.25.14.dist-info/RECORD
